redb/behaviors/__init__.py
redb/behaviors/i_remember.py
redb/behaviors/soft_deletion.py
redb/behaviors/subtypes.py
redb/core/__init__.py
redb/core/base.py
redb/core/document.py
redb/core/instance.py
redb/core/mixins.py
redb/core/transaction.py
redb/core/utils.py
redb/interface/__init__.py
redb/interface/client.py
redb/interface/collection.py
redb/interface/configs.py
redb/interface/database.py
redb/interface/errors.py
redb/interface/fields.py
redb/interface/results.py
redb/json_system/__init__.py
redb/json_system/client.py
redb/json_system/collection.py
redb/json_system/database.py
redb/migo_system/__init__.py
redb/migo_system/client.py
redb/migo_system/collection.py
redb/migo_system/database.py
redb/mongo_system/__init__.py
redb/mongo_system/client.py
redb/mongo_system/collection.py
redb/mongo_system/database.py
redb_odm-1.3.6.dist-info/METADATA
redb_odm-1.3.6.dist-info/WHEEL
redb_odm-1.3.6.dist-info/top_level.txt
redb_odm-1.3.6.dist-info/RECORD
