Metadata-Version: 2.1
Name: redb-odm
Version: 1.3.6
Summary: A python ODM for JSON, Mongo, and Mongo+Milvus.
Home-page: https://github.com/teialabs/redb
Author: Teia Labs
Author-email: contato@teialabs.com
Keywords: database milvus mongo json interface
Requires-Python: >=3.10
Requires-Dist: pydantic <2
Requires-Dist: pymongo
Requires-Dist: pytz
Requires-Dist: typing-extensions
Provides-Extra: all
Requires-Dist: pytest ; extra == 'all'
Requires-Dist: python-dotenv ; extra == 'all'
Requires-Dist: black ; extra == 'all'
Requires-Dist: mypy ; extra == 'all'
Provides-Extra: dev
Requires-Dist: black ; extra == 'dev'
Requires-Dist: mypy ; extra == 'dev'
Requires-Dist: pytest ; extra == 'dev'
Provides-Extra: test
Requires-Dist: pytest ; extra == 'test'
Requires-Dist: python-dotenv ; extra == 'test'
